django_reusable/__init__.py
django_reusable/constants.py
django_reusable/admin/__init__.py
django_reusable/admin/actions.py
django_reusable/admin/filters.py
django_reusable/admin/mixins.py
django_reusable/admin/suit_multi_admin.py
django_reusable/admin/theme.py
django_reusable/admin/urls.py
django_reusable/admin/utils.py
django_reusable/config/__init__.py
django_reusable/config/config.py
django_reusable/config/config_ready_utils.py
django_reusable/config/py_to_ts_interfaces/__init__.py
django_reusable/config/py_to_ts_interfaces/__main__.py
django_reusable/config/py_to_ts_interfaces/enums.py
django_reusable/config/py_to_ts_interfaces/file_io.py
django_reusable/config/py_to_ts_interfaces/interfaces.py
django_reusable/config/py_to_ts_interfaces/strings.py
django_reusable/config/py_to_ts_interfaces/type_converting.py
django_reusable/config/py_to_ts_interfaces/utils.py
django_reusable/db/__init__.py
django_reusable/db/query.py
django_reusable/db/queryset.py
django_reusable/django_tables2/__init__.py
django_reusable/django_tables2/columns.py
django_reusable/django_tables2/table_mixins.py
django_reusable/error_tracker/__init__.py
django_reusable/error_tracker/error_tracker.py
django_reusable/error_tracker/views.py
django_reusable/forms/__init__.py
django_reusable/forms/fields.py
django_reusable/forms/forms.py
django_reusable/forms/validators.py
django_reusable/forms/widgets.py
django_reusable/logging/__init__.py
django_reusable/logging/loggers.py
django_reusable/middleware/__init__.py
django_reusable/middleware/middleware.py
django_reusable/migrations/0001_initial.py
django_reusable/migrations/0002_auto_20250828_0044.py
django_reusable/migrations/__init__.py
django_reusable/models/__init__.py
django_reusable/models/fields.py
django_reusable/models/models.py
django_reusable/static/django_reusable/css/admin/overrides.css
django_reusable/static/django_reusable/js/currency-format.js
django_reusable/static/django_reusable/js/dynamic-formsets.js
django_reusable-13.5.dist-info/AUTHORS
django_reusable-13.5.dist-info/COPYING
django_reusable-13.5.dist-info/METADATA
django_reusable-13.5.dist-info/WHEEL
django_reusable-13.5.dist-info/top_level.txt
django_reusable-13.5.dist-info/RECORD
