Metadata-Version: 2.1
Name: django-reusable
Version: 13.5
Summary: Agnostic and easy to use reusable library for django
Home-page: https://github.com/navedr/django-reusable
Author: Naved Rangwala
Author-email: naved@ecarone.com
License: BSD
Platform: UNKNOWN
Classifier: Development Status :: 5 - Production/Stable
Classifier: Environment :: Web Environment
Classifier: Framework :: Django
Classifier: Intended Audience :: Developers
Classifier: License :: OSI Approved :: BSD License
Classifier: Operating System :: OS Independent
Classifier: Programming Language :: Python
Classifier: Topic :: Utilities
License-File: COPYING
License-File: AUTHORS
Requires-Dist: Django (>=2.0)
Requires-Dist: django-tables2 (>=1.21.2)
Requires-Dist: django-crispy-forms (>=1.7.2)
